{
  "person" : [ {
    "firstname" : "Firstname0",
    "lastname" : "Lastname0",
    "birthdate" : "24-10-2017 12:38",
    "activitypreference" : {
      "name" : "Name0",
      "description" : "Description0",
      "place" : "Place0",
      "startdate" : "24-10-2017 12:38",
      "id" : 100
    },
    "id" : 1
  }, {
    "firstname" : "Firstname1",
    "lastname" : "Lastname1",
    "birthdate" : "24-10-2017 12:38",
    "activitypreference" : {
      "name" : "Name1",
      "description" : "Description1",
      "place" : "Place1",
      "startdate" : "24-10-2017 12:38",
      "id" : 101
    },
    "id" : 2
  }, {
    "firstname" : "Firstname2",
    "lastname" : "Lastname2",
    "birthdate" : "24-10-2017 12:38",
    "activitypreference" : {
      "name" : "Name2",
      "description" : "Description2",
      "place" : "Place2",
      "startdate" : "24-10-2017 12:38",
      "id" : 102
    },
    "id" : 3
  } ]
}